usuarioif/__init__.py
usuarioif/asgi.py
usuarioif/urls.py
usuarioif/wsgi.py
usuarioif-0.1.2.dist-info/METADATA
usuarioif-0.1.2.dist-info/WHEEL
usuarioif-0.1.2.dist-info/RECORD
