Metadata-Version: 2.1
Name: usuarioif
Version: 0.1.2
Summary: 
Author: Caique de Souza
Author-email: Decaiquesouza@gmail.com>, Douglas Rocha <douglasedurocha@gmail.com
Requires-Python: >=3.10,<4.0
Classifier: Programming Language :: Python :: 3
Classifier: Programming Language :: Python :: 3.10
Classifier: Programming Language :: Python :: 3.11
Classifier: Programming Language :: Python :: 3.12
Requires-Dist: django (==3.2.14)
